README.rst
setup.py
bab_cms/__init__.py
bab_cms/admin.py
bab_cms/apps.py
bab_cms/forms.py
bab_cms/models.py
bab_cms/signals.py
bab_cms/tests.py
bab_cms/urls.py
bab_cms/views.py
bab_cms/migrations/0001_initial.py
bab_cms/migrations/__init__.py
bab_cms/templatetags/__init__.py
bab_cms/templatetags/cms_tags.py
django_bab_cms.egg-info/PKG-INFO
django_bab_cms.egg-info/SOURCES.txt
django_bab_cms.egg-info/dependency_links.txt
django_bab_cms.egg-info/top_level.txt